{"upload_date": "20170901", "vcodec": "vp9", "extractor": "youtube", "series": null, "chapters": null, "height": 720, "like_count": 170, "duration": 704, "fulltitle": "\u5e73\u8bbaHot | \u4e0a\u6d77\u8b66\u5bdf\u6253\u4eba\u4e8b\u4ef6\u8ba9\u516c\u4f17\u6000\u5ff5\u6768\u4f73 2017-09-01", "id": "uj3_VDMgBfU", "album": null, "view_count": 32145, "playlist": "Uploads from Weiping Show\u300a\u5e73\u8bba\u300b", "start_time": null, "title": "\u5e73\u8bbaHot | \u4e0a\u6d77\u8b66\u5bdf\u6253\u4eba\u4e8b\u4ef6\u8ba9\u516c\u4f17\u6000\u5ff5\u6768\u4f73 2017-09-01", "_filename": "20170901_uj3_VDMgBfU.webm", "creator": null, "is_live": null, "playlist_index": 338, "dislike_count": 73, "playlist_id": "UU2VwgzDzUNvfRDqQ6LJxTXA", "abr": 160, "tags": [], "uploader_url": "http://www.youtube.com/channel/UC2VwgzDzUNvfRDqQ6LJxTXA", "subtitles": {}, "fps": 30, "stretched_ratio": null, "season_number": null, "annotations": null, "webpage_url_basename": "uj3_VDMgBfU", "acodec": "opus", "display_id": "uj3_VDMgBfU", "automatic_captions": {}, "description": "9\u67081\u65e5\uff0c\u4e0a\u6d77\u677e\u6c5f\u4e24\u4f4d\u8b66\u5bdf\u7c97\u66b4\u6267\u6cd5\uff0c\u5c06\u4e00\u4f4d\u62b1\u7740\u5a74\u513f\u7684\u5987\u5973\u6253\u7ffb\u5728\u5730\uff0c\u5f15\u8d77\u5168\u56fd\u6c11\u6124\uff0c\u6b22\u8fce\u5927\u5bb6\u56f4\u89c2\u672c\u671f\u5e73\u8bba\u3002", "format": "247 - 1280x720 (720p)+251 - audio only (DASH audio)", "track": null, "playlist_uploader": "Weiping Show\u300a\u5e73\u8bba\u300b", "average_rating": 3.7983539, "uploader": "Weiping Show\u300a\u5e73\u8bba\u300b", "format_id": "247+251", "episode_number": null, "uploader_id": "UC2VwgzDzUNvfRDqQ6LJxTXA", "categories": ["News & Politics"], "playlist_title": "Uploads from Weiping Show\u300a\u5e73\u8bba\u300b", "thumbnails": [{"url": "https://i.ytimg.com/vi/uj3_VDMgBfU/maxresdefault.jpg", "id": "0"}], "license": "Creative Commons Attribution license (reuse allowed)", "artist": null, "extractor_key": "Youtube", "release_date": null, "alt_title": null, "channel_id": "UC2VwgzDzUNvfRDqQ6LJxTXA", "thumbnail": "https://i.ytimg.com/vi/uj3_VDMgBfU/maxresdefault.jpg", "vbr": null, "ext": "webm", "release_year": null, "end_time": null, "webpage_url": "https://www.youtube.com/watch?v=uj3_VDMgBfU", "formats": [{"http_headers": {"Accept-Charset": "ISO-8859-1,utf-8;q=0.7,*;q=0.7", "Accept-Language": "en-us,en;q=0.5", "Accept-Encoding": "gzip, deflate", "Accept": "text/html,application/xhtml+xml,application/xml;q=0.9,*/*;q=0.8", "User-Agent": "Mozilla/5.0 (Windows NT 10.0; Win64; x64) AppleWebKit/537.36 (KHTML, like Gecko) Chrome/74.0.3691.1 Safari/537.36"}, "format_note": "DASH audio", "protocol": "https", "format": "249 - audio only (DASH audio)", "url": "https://r2---sn-aigl6ned.googlevideo.com/videoplayback?expire=1565507443&ei=E2tPXez4G-GBsfIP4aqSkAg&ip=148.163.76.139&id=o-AC_G8b3U_emwJfOb8_8I-tYry0CzeWzExgIni8N55XX_&itag=249&source=youtube&requiressl=yes&mm=31%2C29&mn=sn-aigl6ned%2Csn-aigzrn7d&ms=au%2Crdu&mv=u&mvi=1&pl=22&mime=audio%2Fwebm&gir=yes&clen=4355574&dur=704.261&lmt=1504502103812167&mt=1565485147&fvip=2&keepalive=yes&beids=9466585&c=WEB&sparams=expire%2Cei%2Cip%2Cid%2Citag%2Csource%2Crequiressl%2Cmime%2Cgir%2Cclen%2Cdur%2Clmt&sig=ALgxI2wwRgIhAKQ72kmlAim24lCTehC4T15M0Bg6S2w3bdTor3JsGZJaAiEA9irg-Awzc5Ilu-vkYpKej4tuiYC31CJALCjbB8v6tJI%3D&lsparams=mm%2Cmn%2Cms%2Cmv%2Cmvi%2Cpl&lsig=AHylml4wRQIhAJi1xdqJEAdkSskR0gmVp_j0mxhrM87A5V7bjNGAMyr-AiBRm-zs6NdvzkpkYX0Fysyi80N2zoEe827Ckz3UL0v7_w%3D%3D&ratebypass=yes", "vcodec": "none", "tbr": 52.468, "abr": 50, "player_url": "/yts/jsbin/player_ias-vfl0ft1-Z/en_US/base.js", "downloader_options": {"http_chunk_size": 10485760}, "ext": "webm", "filesize": 4355574, "format_id": "249", "quality": -1, "acodec": "opus"}, {"http_headers": {"Accept-Charset": "ISO-8859-1,utf-8;q=0.7,*;q=0.7", "Accept-Language": "en-us,en;q=0.5", "Accept-Encoding": "gzip, deflate", "Accept": "text/html,application/xhtml+xml,application/xml;q=0.9,*/*;q=0.8", "User-Agent": "Mozilla/5.0 (Windows NT 10.0; Win64; x64) AppleWebKit/537.36 (KHTML, like Gecko) Chrome/74.0.3691.1 Safari/537.36"}, "format_note": "DASH audio", "protocol": "https", "format": "250 - audio only (DASH audio)", "url": "https://r2---sn-aigl6ned.googlevideo.com/videoplayback?expire=1565507443&ei=E2tPXez4G-GBsfIP4aqSkAg&ip=148.163.76.139&id=o-AC_G8b3U_emwJfOb8_8I-tYry0CzeWzExgIni8N55XX_&itag=250&source=youtube&requiressl=yes&mm=31%2C29&mn=sn-aigl6ned%2Csn-aigzrn7d&ms=au%2Crdu&mv=u&mvi=1&pl=22&mime=audio%2Fwebm&gir=yes&clen=4746027&dur=704.261&lmt=1504502182651383&mt=1565485147&fvip=2&keepalive=yes&beids=9466585&c=WEB&sparams=expire%2Cei%2Cip%2Cid%2Citag%2Csource%2Crequiressl%2Cmime%2Cgir%2Cclen%2Cdur%2Clmt&sig=ALgxI2wwRAIgJlR-ye2SmeaZBBvL57E9PU-F4d09tNhOePMCNTxD_wQCIFcdmEgkZd2pdiK7_lk2ijXlG2iTj7XrKg-rhJ5UxXPR&lsparams=mm%2Cmn%2Cms%2Cmv%2Cmvi%2Cpl&lsig=AHylml4wRQIhAJi1xdqJEAdkSskR0gmVp_j0mxhrM87A5V7bjNGAMyr-AiBRm-zs6NdvzkpkYX0Fysyi80N2zoEe827Ckz3UL0v7_w%3D%3D&ratebypass=yes", "vcodec": "none", "tbr": 66.27, "abr": 70, "player_url": "/yts/jsbin/player_ias-vfl0ft1-Z/en_US/base.js", "downloader_options": {"http_chunk_size": 10485760}, "ext": "webm", "filesize": 4746027, "format_id": "250", "quality": -1, "acodec": "opus"}, {"http_headers": {"Accept-Charset": "ISO-8859-1,utf-8;q=0.7,*;q=0.7", "Accept-Language": "en-us,en;q=0.5", "Accept-Encoding": "gzip, deflate", "Accept": "text/html,application/xhtml+xml,application/xml;q=0.9,*/*;q=0.8", "User-Agent": "Mozilla/5.0 (Windows NT 10.0; Win64; x64) AppleWebKit/537.36 (KHTML, like Gecko) Chrome/74.0.3691.1 Safari/537.36"}, "tbr": 128.55, "container": "m4a_dash", "format": "140 - audio only (DASH audio)", "url": "https://r2---sn-aigl6ned.googlevideo.com/videoplayback?expire=1565507443&ei=E2tPXez4G-GBsfIP4aqSkAg&ip=148.163.76.139&id=o-AC_G8b3U_emwJfOb8_8I-tYry0CzeWzExgIni8N55XX_&itag=140&source=youtube&requiressl=yes&mm=31%2C29&mn=sn-aigl6ned%2Csn-aigzrn7d&ms=au%2Crdu&mv=u&mvi=1&pl=22&mime=audio%2Fmp4&gir=yes&clen=11187155&dur=704.330&lmt=1504500755780533&mt=1565485147&fvip=2&keepalive=yes&beids=9466585&c=WEB&sparams=expire%2Cei%2Cip%2Cid%2Citag%2Csource%2Crequiressl%2Cmime%2Cgir%2Cclen%2Cdur%2Clmt&sig=ALgxI2wwRgIhAOJ4zqAy9lSUSUboIl8-CbyiQD_DXT5-MZ1IkCegSihvAiEAz-dcoajwEWgT92Kg5a5hud6Klfq8m1NA1lE-62YZNfQ%3D&lsparams=mm%2Cmn%2Cms%2Cmv%2Cmvi%2Cpl&lsig=AHylml4wRQIhAJi1xdqJEAdkSskR0gmVp_j0mxhrM87A5V7bjNGAMyr-AiBRm-zs6NdvzkpkYX0Fysyi80N2zoEe827Ckz3UL0v7_w%3D%3D&ratebypass=yes", "vcodec": "none", "format_note": "DASH audio", "abr": 128, "player_url": "/yts/jsbin/player_ias-vfl0ft1-Z/en_US/base.js", "downloader_options": {"http_chunk_size": 10485760}, "ext": "m4a", "filesize": 11187155, "protocol": "https", "format_id": "140", "quality": -1, "acodec": "mp4a.40.2"}, {"http_headers": {"Accept-Charset": "ISO-8859-1,utf-8;q=0.7,*;q=0.7", "Accept-Language": "en-us,en;q=0.5", "Accept-Encoding": "gzip, deflate", "Accept": "text/html,application/xhtml+xml,application/xml;q=0.9,*/*;q=0.8", "User-Agent": "Mozilla/5.0 (Windows NT 10.0; Win64; x64) AppleWebKit/537.36 (KHTML, like Gecko) Chrome/74.0.3691.1 Safari/537.36"}, "format_note": "DASH audio", "protocol": "https", "format": "251 - audio only (DASH audio)", "url": "https://r2---sn-aigl6ned.googlevideo.com/videoplayback?expire=1565507443&ei=E2tPXez4G-GBsfIP4aqSkAg&ip=148.163.76.139&id=o-AC_G8b3U_emwJfOb8_8I-tYry0CzeWzExgIni8N55XX_&itag=251&source=youtube&requiressl=yes&mm=31%2C29&mn=sn-aigl6ned%2Csn-aigzrn7d&ms=au%2Crdu&mv=u&mvi=1&pl=22&mime=audio%2Fwebm&gir=yes&clen=8577598&dur=704.261&lmt=1504502105232056&mt=1565485147&fvip=2&keepalive=yes&beids=9466585&c=WEB&sparams=expire%2Cei%2Cip%2Cid%2Citag%2Csource%2Crequiressl%2Cmime%2Cgir%2Cclen%2Cdur%2Clmt&sig=ALgxI2wwRQIhAMBbc9Lu_WF-gOWb40__0Dt8K2Wit3jMKDmnTpLUDI5jAiAuq2flEZuVkkGcUxR2bmfEtXHiKS4rUT-O_kubQTPH6g%3D%3D&lsparams=mm%2Cmn%2Cms%2Cmv%2Cmvi%2Cpl&lsig=AHylml4wRQIhAJi1xdqJEAdkSskR0gmVp_j0mxhrM87A5V7bjNGAMyr-AiBRm-zs6NdvzkpkYX0Fysyi80N2zoEe827Ckz3UL0v7_w%3D%3D&ratebypass=yes", "vcodec": "none", "tbr": 130.597, "abr": 160, "player_url": "/yts/jsbin/player_ias-vfl0ft1-Z/en_US/base.js", "downloader_options": {"http_chunk_size": 10485760}, "ext": "webm", "filesize": 8577598, "format_id": "251", "quality": -1, "acodec": "opus"}, {"format_note": "144p", "protocol": "https", "format": "160 - 256x144 (144p)", "tbr": 82.825, "height": 144, "downloader_options": {"http_chunk_size": 10485760}, "format_id": "160", "quality": -1, "http_headers": {"Accept-Charset": "ISO-8859-1,utf-8;q=0.7,*;q=0.7", "Accept-Language": "en-us,en;q=0.5", "Accept-Encoding": "gzip, deflate", "Accept": "text/html,application/xhtml+xml,application/xml;q=0.9,*/*;q=0.8", "User-Agent": "Mozilla/5.0 (Windows NT 10.0; Win64; x64) AppleWebKit/537.36 (KHTML, like Gecko) Chrome/74.0.3691.1 Safari/537.36"}, "url": "https://r2---sn-aigl6ned.googlevideo.com/videoplayback?expire=1565507443&ei=E2tPXez4G-GBsfIP4aqSkAg&ip=148.163.76.139&id=o-AC_G8b3U_emwJfOb8_8I-tYry0CzeWzExgIni8N55XX_&itag=160&aitags=133%2C134%2C135%2C136%2C160%2C242%2C243%2C244%2C247%2C278&source=youtube&requiressl=yes&mm=31%2C29&mn=sn-aigl6ned%2Csn-aigzrn7d&ms=au%2Crdu&mv=u&mvi=1&pl=22&mime=video%2Fmp4&gir=yes&clen=2323975&dur=704.266&lmt=1504500743792971&mt=1565485147&fvip=2&keepalive=yes&beids=9466585&c=WEB&sparams=expire%2Cei%2Cip%2Cid%2Caitags%2Csource%2Crequiressl%2Cmime%2Cgir%2Cclen%2Cdur%2Clmt&sig=ALgxI2wwRQIgTqjn9HGa92HiP39NC2n3nWm_1t568zavONJiNwt-WtgCIQCRv959h661POd9LGdhocm1VqN43cG2nR26kLKQdMcx8g%3D%3D&lsparams=mm%2Cmn%2Cms%2Cmv%2Cmvi%2Cpl&lsig=AHylml4wRQIhAJi1xdqJEAdkSskR0gmVp_j0mxhrM87A5V7bjNGAMyr-AiBRm-zs6NdvzkpkYX0Fysyi80N2zoEe827Ckz3UL0v7_w%3D%3D&ratebypass=yes", "vcodec": "avc1.4d400c", "player_url": "/yts/jsbin/player_ias-vfl0ft1-Z/en_US/base.js", "width": 256, "ext": "mp4", "filesize": 2323975, "fps": 30, "acodec": "none"}, {"http_headers": {"Accept-Charset": "ISO-8859-1,utf-8;q=0.7,*;q=0.7", "Accept-Language": "en-us,en;q=0.5", "Accept-Encoding": "gzip, deflate", "Accept": "text/html,application/xhtml+xml,application/xml;q=0.9,*/*;q=0.8", "User-Agent": "Mozilla/5.0 (Windows NT 10.0; Win64; x64) AppleWebKit/537.36 (KHTML, like Gecko) Chrome/74.0.3691.1 Safari/537.36"}, "tbr": 103.496, "container": "webm", "format": "278 - 256x144 (144p)", "url": "https://r2---sn-aigl6ned.googlevideo.com/videoplayback?expire=1565507443&ei=E2tPXez4G-GBsfIP4aqSkAg&ip=148.163.76.139&id=o-AC_G8b3U_emwJfOb8_8I-tYry0CzeWzExgIni8N55XX_&itag=278&aitags=133%2C134%2C135%2C136%2C160%2C242%2C243%2C244%2C247%2C278&source=youtube&requiressl=yes&mm=31%2C29&mn=sn-aigl6ned%2Csn-aigzrn7d&ms=au%2Crdu&mv=u&mvi=1&pl=22&mime=video%2Fwebm&gir=yes&clen=7500265&dur=704.234&lmt=1504502422760380&mt=1565485147&fvip=2&keepalive=yes&beids=9466585&c=WEB&sparams=expire%2Cei%2Cip%2Cid%2Caitags%2Csource%2Crequiressl%2Cmime%2Cgir%2Cclen%2Cdur%2Clmt&sig=ALgxI2wwRQIhAOSvS-KTSsDhM20KihujL3UPwRUezgB0vsJ2TBDXubrJAiAn-jkw5mhO4eSCVKd878ITckhrSYENCfxdC6wPT2MZcg%3D%3D&lsparams=mm%2Cmn%2Cms%2Cmv%2Cmvi%2Cpl&lsig=AHylml4wRQIhAJi1xdqJEAdkSskR0gmVp_j0mxhrM87A5V7bjNGAMyr-AiBRm-zs6NdvzkpkYX0Fysyi80N2zoEe827Ckz3UL0v7_w%3D%3D&ratebypass=yes", "vcodec": "vp9", "format_note": "144p", "player_url": "/yts/jsbin/player_ias-vfl0ft1-Z/en_US/base.js", "downloader_options": {"http_chunk_size": 10485760}, "width": 256, "ext": "webm", "filesize": 7500265, "fps": 30, "protocol": "https", "format_id": "278", "height": 144, "quality": -1, "acodec": "none"}, {"format_note": "240p", "protocol": "https", "format": "133 - 426x240 (240p)", "tbr": 147.549, "height": 240, "downloader_options": {"http_chunk_size": 10485760}, "format_id": "133", "quality": -1, "http_headers": {"Accept-Charset": "ISO-8859-1,utf-8;q=0.7,*;q=0.7", "Accept-Language": "en-us,en;q=0.5", "Accept-Encoding": "gzip, deflate", "Accept": "text/html,application/xhtml+xml,application/xml;q=0.9,*/*;q=0.8", "User-Agent": "Mozilla/5.0 (Windows NT 10.0; Win64; x64) AppleWebKit/537.36 (KHTML, like Gecko) Chrome/74.0.3691.1 Safari/537.36"}, "url": "https://r2---sn-aigl6ned.googlevideo.com/videoplayback?expire=1565507443&ei=E2tPXez4G-GBsfIP4aqSkAg&ip=148.163.76.139&id=o-AC_G8b3U_emwJfOb8_8I-tYry0CzeWzExgIni8N55XX_&itag=133&aitags=133%2C134%2C135%2C136%2C160%2C242%2C243%2C244%2C247%2C278&source=youtube&requiressl=yes&mm=31%2C29&mn=sn-aigl6ned%2Csn-aigzrn7d&ms=au%2Crdu&mv=u&mvi=1&pl=22&mime=video%2Fmp4&gir=yes&clen=3965122&dur=704.266&lmt=1504500743999324&mt=1565485147&fvip=2&keepalive=yes&beids=9466585&c=WEB&sparams=expire%2Cei%2Cip%2Cid%2Caitags%2Csource%2Crequiressl%2Cmime%2Cgir%2Cclen%2Cdur%2Clmt&sig=ALgxI2wwRgIhAIZpdhF8cADlsTs2lbpczxk_QYPhaXN1S3I2etJkpRzMAiEA2SHf2ogIez1-5RmsZqufxuDCcevpFW4v6erW7KEqSUU%3D&lsparams=mm%2Cmn%2Cms%2Cmv%2Cmvi%2Cpl&lsig=AHylml4wRQIhAJi1xdqJEAdkSskR0gmVp_j0mxhrM87A5V7bjNGAMyr-AiBRm-zs6NdvzkpkYX0Fysyi80N2zoEe827Ckz3UL0v7_w%3D%3D&ratebypass=yes", "vcodec": "avc1.4d4015", "player_url": "/yts/jsbin/player_ias-vfl0ft1-Z/en_US/base.js", "width": 426, "ext": "mp4", "filesize": 3965122, "fps": 30, "acodec": "none"}, {"format_note": "240p", "protocol": "https", "format": "242 - 426x240 (240p)", "tbr": 242.543, "height": 240, "downloader_options": {"http_chunk_size": 10485760}, "format_id": "242", "quality": -1, "http_headers": {"Accept-Charset": "ISO-8859-1,utf-8;q=0.7,*;q=0.7", "Accept-Language": "en-us,en;q=0.5", "Accept-Encoding": "gzip, deflate", "Accept": "text/html,application/xhtml+xml,application/xml;q=0.9,*/*;q=0.8", "User-Agent": "Mozilla/5.0 (Windows NT 10.0; Win64; x64) AppleWebKit/537.36 (KHTML, like Gecko) Chrome/74.0.3691.1 Safari/537.36"}, "url": "https://r2---sn-aigl6ned.googlevideo.com/videoplayback?expire=1565507443&ei=E2tPXez4G-GBsfIP4aqSkAg&ip=148.163.76.139&id=o-AC_G8b3U_emwJfOb8_8I-tYry0CzeWzExgIni8N55XX_&itag=242&aitags=133%2C134%2C135%2C136%2C160%2C242%2C243%2C244%2C247%2C278&source=youtube&requiressl=yes&mm=31%2C29&mn=sn-aigl6ned%2Csn-aigzrn7d&ms=au%2Crdu&mv=u&mvi=1&pl=22&mime=video%2Fwebm&gir=yes&clen=8689948&dur=704.234&lmt=1504502424598295&mt=1565485147&fvip=2&keepalive=yes&beids=9466585&c=WEB&sparams=expire%2Cei%2Cip%2Cid%2Caitags%2Csource%2Crequiressl%2Cmime%2Cgir%2Cclen%2Cdur%2Clmt&sig=ALgxI2wwRgIhALVUDgyKl1tN-755HCks2FnkOzcwyQPGA_O9pNbpS4YBAiEA1IffBELg5CRzoGDlY3dJ667YOUTtYUfqKxRomffRCUw%3D&lsparams=mm%2Cmn%2Cms%2Cmv%2Cmvi%2Cpl&lsig=AHylml4wRQIhAJi1xdqJEAdkSskR0gmVp_j0mxhrM87A5V7bjNGAMyr-AiBRm-zs6NdvzkpkYX0Fysyi80N2zoEe827Ckz3UL0v7_w%3D%3D&ratebypass=yes", "vcodec": "vp9", "player_url": "/yts/jsbin/player_ias-vfl0ft1-Z/en_US/base.js", "width": 426, "ext": "webm", "filesize": 8689948, "fps": 30, "acodec": "none"}, {"format_note": "360p", "protocol": "https", "format": "134 - 640x360 (360p)", "tbr": 329.121, "height": 360, "downloader_options": {"http_chunk_size": 10485760}, "format_id": "134", "quality": -1, "http_headers": {"Accept-Charset": "ISO-8859-1,utf-8;q=0.7,*;q=0.7", "Accept-Language": "en-us,en;q=0.5", "Accept-Encoding": "gzip, deflate", "Accept": "text/html,application/xhtml+xml,application/xml;q=0.9,*/*;q=0.8", "User-Agent": "Mozilla/5.0 (Windows NT 10.0; Win64; x64) AppleWebKit/537.36 (KHTML, like Gecko) Chrome/74.0.3691.1 Safari/537.36"}, "url": "https://r2---sn-aigl6ned.googlevideo.com/videoplayback?expire=1565507443&ei=E2tPXez4G-GBsfIP4aqSkAg&ip=148.163.76.139&id=o-AC_G8b3U_emwJfOb8_8I-tYry0CzeWzExgIni8N55XX_&itag=134&aitags=133%2C134%2C135%2C136%2C160%2C242%2C243%2C244%2C247%2C278&source=youtube&requiressl=yes&mm=31%2C29&mn=sn-aigl6ned%2Csn-aigzrn7d&ms=au%2Crdu&mv=u&mvi=1&pl=22&mime=video%2Fmp4&gir=yes&clen=9573141&dur=704.266&lmt=1504500744205884&mt=1565485147&fvip=2&keepalive=yes&beids=9466585&c=WEB&sparams=expire%2Cei%2Cip%2Cid%2Caitags%2Csource%2Crequiressl%2Cmime%2Cgir%2Cclen%2Cdur%2Clmt&sig=ALgxI2wwRgIhAPFANdLxys9wm7dIcyet-PkPDMk45kTjBOBdzqcARrhhAiEA-oqLJ4izokkT98poSRA9dL3O8BrziQo9WMPr7SHpJWM%3D&lsparams=mm%2Cmn%2Cms%2Cmv%2Cmvi%2Cpl&lsig=AHylml4wRQIhAJi1xdqJEAdkSskR0gmVp_j0mxhrM87A5V7bjNGAMyr-AiBRm-zs6NdvzkpkYX0Fysyi80N2zoEe827Ckz3UL0v7_w%3D%3D&ratebypass=yes", "vcodec": "avc1.4d401e", "player_url": "/yts/jsbin/player_ias-vfl0ft1-Z/en_US/base.js", "width": 640, "ext": "mp4", "filesize": 9573141, "fps": 30, "acodec": "none"}, {"format_note": "360p", "protocol": "https", "format": "243 - 640x360 (360p)", "tbr": 435.992, "height": 360, "downloader_options": {"http_chunk_size": 10485760}, "format_id": "243", "quality": -1, "http_headers": {"Accept-Charset": "ISO-8859-1,utf-8;q=0.7,*;q=0.7", "Accept-Language": "en-us,en;q=0.5", "Accept-Encoding": "gzip, deflate", "Accept": "text/html,application/xhtml+xml,application/xml;q=0.9,*/*;q=0.8", "User-Agent": "Mozilla/5.0 (Windows NT 10.0; Win64; x64) AppleWebKit/537.36 (KHTML, like Gecko) Chrome/74.0.3691.1 Safari/537.36"}, "url": "https://r2---sn-aigl6ned.googlevideo.com/videoplayback?expire=1565507443&ei=E2tPXez4G-GBsfIP4aqSkAg&ip=148.163.76.139&id=o-AC_G8b3U_emwJfOb8_8I-tYry0CzeWzExgIni8N55XX_&itag=243&aitags=133%2C134%2C135%2C136%2C160%2C242%2C243%2C244%2C247%2C278&source=youtube&requiressl=yes&mm=31%2C29&mn=sn-aigl6ned%2Csn-aigzrn7d&ms=au%2Crdu&mv=u&mvi=1&pl=22&mime=video%2Fwebm&gir=yes&clen=17906191&dur=704.234&lmt=1504502426250993&mt=1565485147&fvip=2&keepalive=yes&beids=9466585&c=WEB&sparams=expire%2Cei%2Cip%2Cid%2Caitags%2Csource%2Crequiressl%2Cmime%2Cgir%2Cclen%2Cdur%2Clmt&sig=ALgxI2wwRQIhAI9Z8lkZKZeHxXYsBRkKQVKEW0HYOe-E6es6ebJBK2hzAiBdypgnDLg4eZn8b5m7F8UCzD9gzC4DQLkCc4y558cmTQ%3D%3D&lsparams=mm%2Cmn%2Cms%2Cmv%2Cmvi%2Cpl&lsig=AHylml4wRQIhAJi1xdqJEAdkSskR0gmVp_j0mxhrM87A5V7bjNGAMyr-AiBRm-zs6NdvzkpkYX0Fysyi80N2zoEe827Ckz3UL0v7_w%3D%3D&ratebypass=yes", "vcodec": "vp9", "player_url": "/yts/jsbin/player_ias-vfl0ft1-Z/en_US/base.js", "width": 640, "ext": "webm", "filesize": 17906191, "fps": 30, "acodec": "none"}, {"format_note": "480p", "protocol": "https", "format": "135 - 854x480 (480p)", "tbr": 589.834, "height": 480, "downloader_options": {"http_chunk_size": 10485760}, "format_id": "135", "quality": -1, "http_headers": {"Accept-Charset": "ISO-8859-1,utf-8;q=0.7,*;q=0.7", "Accept-Language": "en-us,en;q=0.5", "Accept-Encoding": "gzip, deflate", "Accept": "text/html,application/xhtml+xml,application/xml;q=0.9,*/*;q=0.8", "User-Agent": "Mozilla/5.0 (Windows NT 10.0; Win64; x64) AppleWebKit/537.36 (KHTML, like Gecko) Chrome/74.0.3691.1 Safari/537.36"}, "url": "https://r2---sn-aigl6ned.googlevideo.com/videoplayback?expire=1565507443&ei=E2tPXez4G-GBsfIP4aqSkAg&ip=148.163.76.139&id=o-AC_G8b3U_emwJfOb8_8I-tYry0CzeWzExgIni8N55XX_&itag=135&aitags=133%2C134%2C135%2C136%2C160%2C242%2C243%2C244%2C247%2C278&source=youtube&requiressl=yes&mm=31%2C29&mn=sn-aigl6ned%2Csn-aigzrn7d&ms=au%2Crdu&mv=u&mvi=1&pl=22&mime=video%2Fmp4&gir=yes&clen=19203835&dur=704.266&lmt=1504500744292531&mt=1565485147&fvip=2&keepalive=yes&beids=9466585&c=WEB&sparams=expire%2Cei%2Cip%2Cid%2Caitags%2Csource%2Crequiressl%2Cmime%2Cgir%2Cclen%2Cdur%2Clmt&sig=ALgxI2wwRQIgFME0FoMKr9_FTVPyqXOzMTIyfZOGvLAqVDPqN8-QLbcCIQDGt4UxUldvl7UJy-I7O3RpBZeuHVr9r8-mW2GKsYAaRA%3D%3D&lsparams=mm%2Cmn%2Cms%2Cmv%2Cmvi%2Cpl&lsig=AHylml4wRQIhAJi1xdqJEAdkSskR0gmVp_j0mxhrM87A5V7bjNGAMyr-AiBRm-zs6NdvzkpkYX0Fysyi80N2zoEe827Ckz3UL0v7_w%3D%3D&ratebypass=yes", "vcodec": "avc1.4d401f", "player_url": "/yts/jsbin/player_ias-vfl0ft1-Z/en_US/base.js", "width": 854, "ext": "mp4", "filesize": 19203835, "fps": 30, "acodec": "none"}, {"format_note": "480p", "protocol": "https", "format": "244 - 854x480 (480p)", "tbr": 746.304, "height": 480, "downloader_options": {"http_chunk_size": 10485760}, "format_id": "244", "quality": -1, "http_headers": {"Accept-Charset": "ISO-8859-1,utf-8;q=0.7,*;q=0.7", "Accept-Language": "en-us,en;q=0.5", "Accept-Encoding": "gzip, deflate", "Accept": "text/html,application/xhtml+xml,application/xml;q=0.9,*/*;q=0.8", "User-Agent": "Mozilla/5.0 (Windows NT 10.0; Win64; x64) AppleWebKit/537.36 (KHTML, like Gecko) Chrome/74.0.3691.1 Safari/537.36"}, "url": "https://r2---sn-aigl6ned.googlevideo.com/videoplayback?expire=1565507443&ei=E2tPXez4G-GBsfIP4aqSkAg&ip=148.163.76.139&id=o-AC_G8b3U_emwJfOb8_8I-tYry0CzeWzExgIni8N55XX_&itag=244&aitags=133%2C134%2C135%2C136%2C160%2C242%2C243%2C244%2C247%2C278&source=youtube&requiressl=yes&mm=31%2C29&mn=sn-aigl6ned%2Csn-aigzrn7d&ms=au%2Crdu&mv=u&mvi=1&pl=22&mime=video%2Fwebm&gir=yes&clen=31120662&dur=704.234&lmt=1504502424916524&mt=1565485147&fvip=2&keepalive=yes&beids=9466585&c=WEB&sparams=expire%2Cei%2Cip%2Cid%2Caitags%2Csource%2Crequiressl%2Cmime%2Cgir%2Cclen%2Cdur%2Clmt&sig=ALgxI2wwRgIhALiwghbdRxdHVpkAbAEtaCeG26PGDO3ZQKG2Zuj8BPIVAiEAh7hSG_3tTuQuwjacZtkWkqsNvEJdvCyZlun_mSQZLX8%3D&lsparams=mm%2Cmn%2Cms%2Cmv%2Cmvi%2Cpl&lsig=AHylml4wRQIhAJi1xdqJEAdkSskR0gmVp_j0mxhrM87A5V7bjNGAMyr-AiBRm-zs6NdvzkpkYX0Fysyi80N2zoEe827Ckz3UL0v7_w%3D%3D&ratebypass=yes", "vcodec": "vp9", "player_url": "/yts/jsbin/player_ias-vfl0ft1-Z/en_US/base.js", "width": 854, "ext": "webm", "filesize": 31120662, "fps": 30, "acodec": "none"}, {"format_note": "720p", "protocol": "https", "format": "136 - 1280x720 (720p)", "tbr": 1076.35, "height": 720, "downloader_options": {"http_chunk_size": 10485760}, "format_id": "136", "quality": -1, "http_headers": {"Accept-Charset": "ISO-8859-1,utf-8;q=0.7,*;q=0.7", "Accept-Language": "en-us,en;q=0.5", "Accept-Encoding": "gzip, deflate", "Accept": "text/html,application/xhtml+xml,application/xml;q=0.9,*/*;q=0.8", "User-Agent": "Mozilla/5.0 (Windows NT 10.0; Win64; x64) AppleWebKit/537.36 (KHTML, like Gecko) Chrome/74.0.3691.1 Safari/537.36"}, "url": "https://r2---sn-aigl6ned.googlevideo.com/videoplayback?expire=1565507443&ei=E2tPXez4G-GBsfIP4aqSkAg&ip=148.163.76.139&id=o-AC_G8b3U_emwJfOb8_8I-tYry0CzeWzExgIni8N55XX_&itag=136&aitags=133%2C134%2C135%2C136%2C160%2C242%2C243%2C244%2C247%2C278&source=youtube&requiressl=yes&mm=31%2C29&mn=sn-aigl6ned%2Csn-aigzrn7d&ms=au%2Crdu&mv=u&mvi=1&pl=22&mime=video%2Fmp4&gir=yes&clen=43434247&dur=704.266&lmt=1504500744089893&mt=1565485147&fvip=2&keepalive=yes&beids=9466585&c=WEB&sparams=expire%2Cei%2Cip%2Cid%2Caitags%2Csource%2Crequiressl%2Cmime%2Cgir%2Cclen%2Cdur%2Clmt&sig=ALgxI2wwRQIgKoT8DMGNtq8Q-k1S_5DHgKsdsCHucJdSoXVS-2sxDYcCIQDxjEy0gJnf04D67_7ani4qaQML3Jt8TCE2PT8vbkSGiw%3D%3D&lsparams=mm%2Cmn%2Cms%2Cmv%2Cmvi%2Cpl&lsig=AHylml4wRQIhAJi1xdqJEAdkSskR0gmVp_j0mxhrM87A5V7bjNGAMyr-AiBRm-zs6NdvzkpkYX0Fysyi80N2zoEe827Ckz3UL0v7_w%3D%3D&ratebypass=yes", "vcodec": "avc1.4d401f", "player_url": "/yts/jsbin/player_ias-vfl0ft1-Z/en_US/base.js", "width": 1280, "ext": "mp4", "filesize": 43434247, "fps": 30, "acodec": "none"}, {"format_note": "720p", "protocol": "https", "format": "247 - 1280x720 (720p)", "tbr": 1381.757, "height": 720, "downloader_options": {"http_chunk_size": 10485760}, "format_id": "247", "quality": -1, "http_headers": {"Accept-Charset": "ISO-8859-1,utf-8;q=0.7,*;q=0.7", "Accept-Language": "en-us,en;q=0.5", "Accept-Encoding": "gzip, deflate", "Accept": "text/html,application/xhtml+xml,application/xml;q=0.9,*/*;q=0.8", "User-Agent": "Mozilla/5.0 (Windows NT 10.0; Win64; x64) AppleWebKit/537.36 (KHTML, like Gecko) Chrome/74.0.3691.1 Safari/537.36"}, "url": "https://r2---sn-aigl6ned.googlevideo.com/videoplayback?expire=1565507443&ei=E2tPXez4G-GBsfIP4aqSkAg&ip=148.163.76.139&id=o-AC_G8b3U_emwJfOb8_8I-tYry0CzeWzExgIni8N55XX_&itag=247&aitags=133%2C134%2C135%2C136%2C160%2C242%2C243%2C244%2C247%2C278&source=youtube&requiressl=yes&mm=31%2C29&mn=sn-aigl6ned%2Csn-aigzrn7d&ms=au%2Crdu&mv=u&mvi=1&pl=22&mime=video%2Fwebm&gir=yes&clen=68062534&dur=704.234&lmt=1504502428521177&mt=1565485147&fvip=2&keepalive=yes&beids=9466585&c=WEB&sparams=expire%2Cei%2Cip%2Cid%2Caitags%2Csource%2Crequiressl%2Cmime%2Cgir%2Cclen%2Cdur%2Clmt&sig=ALgxI2wwRQIgWEs7zJSzkATx-X2ZBTh-hxOzXAaAZXJ0YcdR-QFWyncCIQCEg7FERXvoAIiUXN2n4oEiW0FgnRSTgPeF0zblbPWXBA%3D%3D&lsparams=mm%2Cmn%2Cms%2Cmv%2Cmvi%2Cpl&lsig=AHylml4wRQIhAJi1xdqJEAdkSskR0gmVp_j0mxhrM87A5V7bjNGAMyr-AiBRm-zs6NdvzkpkYX0Fysyi80N2zoEe827Ckz3UL0v7_w%3D%3D&ratebypass=yes", "vcodec": "vp9", "player_url": "/yts/jsbin/player_ias-vfl0ft1-Z/en_US/base.js", "width": 1280, "ext": "webm", "filesize": 68062534, "fps": 30, "acodec": "none"}, {"asr": null, "format_note": "medium", "protocol": "https", "http_headers": {"Accept-Charset": "ISO-8859-1,utf-8;q=0.7,*;q=0.7", "Accept-Language": "en-us,en;q=0.5", "Accept-Encoding": "gzip, deflate", "Accept": "text/html,application/xhtml+xml,application/xml;q=0.9,*/*;q=0.8", "User-Agent": "Mozilla/5.0 (Windows NT 10.0; Win64; x64) AppleWebKit/537.36 (KHTML, like Gecko) Chrome/74.0.3691.1 Safari/537.36"}, "format": "43 - 640x360 (medium)", "url": "https://r2---sn-aigl6ned.googlevideo.com/videoplayback?expire=1565507443&ei=E2tPXez4G-GBsfIP4aqSkAg&ip=148.163.76.139&id=o-AC_G8b3U_emwJfOb8_8I-tYry0CzeWzExgIni8N55XX_&itag=43&source=youtube&requiressl=yes&mm=31%2C29&mn=sn-aigl6ned%2Csn-aigzrn7d&ms=au%2Crdu&mv=u&mvi=1&pl=22&mime=video%2Fwebm&gir=yes&clen=45309274&ratebypass=yes&dur=0.000&lmt=1504502373616580&mt=1565485147&fvip=2&beids=9466585&c=WEB&sparams=expire%2Cei%2Cip%2Cid%2Citag%2Csource%2Crequiressl%2Cmime%2Cgir%2Cclen%2Cratebypass%2Cdur%2Clmt&sig=ALgxI2wwRQIhAMwLb7czPFsdwA_kzCvrDHjwO3uTilcEHGEvcovml1f9AiBYOmQBCBQ004g3WV3UjvGmCHQHh6ecxvknZBebuvtCmg%3D%3D&lsparams=mm%2Cmn%2Cms%2Cmv%2Cmvi%2Cpl&lsig=AHylml4wRQIhAJi1xdqJEAdkSskR0gmVp_j0mxhrM87A5V7bjNGAMyr-AiBRm-zs6NdvzkpkYX0Fysyi80N2zoEe827Ckz3UL0v7_w%3D%3D", "vcodec": "vp8.0", "tbr": null, "ext": "webm", "player_url": "/yts/jsbin/player_ias-vfl0ft1-Z/en_US/base.js", "width": 640, "abr": 128, "filesize": 45309274, "fps": null, "format_id": "43", "height": 360, "quality": 1, "acodec": "vorbis"}, {"asr": 44100, "format_note": "medium", "protocol": "https", "http_headers": {"Accept-Charset": "ISO-8859-1,utf-8;q=0.7,*;q=0.7", "Accept-Language": "en-us,en;q=0.5", "Accept-Encoding": "gzip, deflate", "Accept": "text/html,application/xhtml+xml,application/xml;q=0.9,*/*;q=0.8", "User-Agent": "Mozilla/5.0 (Windows NT 10.0; Win64; x64) AppleWebKit/537.36 (KHTML, like Gecko) Chrome/74.0.3691.1 Safari/537.36"}, "format": "18 - 640x360 (medium)", "url": "https://r2---sn-aigl6ned.googlevideo.com/videoplayback?expire=1565507443&ei=E2tPXez4G-GBsfIP4aqSkAg&ip=148.163.76.139&id=o-AC_G8b3U_emwJfOb8_8I-tYry0CzeWzExgIni8N55XX_&itag=18&source=youtube&requiressl=yes&mm=31%2C29&mn=sn-aigl6ned%2Csn-aigzrn7d&ms=au%2Crdu&mv=u&mvi=1&pl=22&mime=video%2Fmp4&gir=yes&clen=32375107&ratebypass=yes&dur=704.330&lmt=1504500821150273&mt=1565485147&fvip=2&beids=9466585&c=WEB&sparams=expire%2Cei%2Cip%2Cid%2Citag%2Csource%2Crequiressl%2Cmime%2Cgir%2Cclen%2Cratebypass%2Cdur%2Clmt&sig=ALgxI2wwRgIhAILCPVam8IycfJh0xkH77-zWpY1X0Sf2RKKbDGv6USy0AiEA5mSzPyUtHpJkK3mgl5eKma5A-b95JgeVeluVwNDRBkw%3D&lsparams=mm%2Cmn%2Cms%2Cmv%2Cmvi%2Cpl&lsig=AHylml4wRQIhAJi1xdqJEAdkSskR0gmVp_j0mxhrM87A5V7bjNGAMyr-AiBRm-zs6NdvzkpkYX0Fysyi80N2zoEe827Ckz3UL0v7_w%3D%3D", "vcodec": "avc1.42001E", "tbr": 367.726, "ext": "mp4", "player_url": "/yts/jsbin/player_ias-vfl0ft1-Z/en_US/base.js", "width": 640, "abr": 96, "filesize": 32375107, "fps": null, "format_id": "18", "height": 360, "quality": 1, "acodec": "mp4a.40.2"}, {"asr": 44100, "format_note": "hd720", "protocol": "https", "http_headers": {"Accept-Charset": "ISO-8859-1,utf-8;q=0.7,*;q=0.7", "Accept-Language": "en-us,en;q=0.5", "Accept-Encoding": "gzip, deflate", "Accept": "text/html,application/xhtml+xml,application/xml;q=0.9,*/*;q=0.8", "User-Agent": "Mozilla/5.0 (Windows NT 10.0; Win64; x64) AppleWebKit/537.36 (KHTML, like Gecko) Chrome/74.0.3691.1 Safari/537.36"}, "format": "22 - 1280x720 (hd720)", "url": "https://r2---sn-aigl6ned.googlevideo.com/videoplayback?expire=1565507443&ei=E2tPXez4G-GBsfIP4aqSkAg&ip=148.163.76.139&id=o-AC_G8b3U_emwJfOb8_8I-tYry0CzeWzExgIni8N55XX_&itag=22&source=youtube&requiressl=yes&mm=31%2C29&mn=sn-aigl6ned%2Csn-aigzrn7d&ms=au%2Crdu&mv=u&mvi=1&pl=22&mime=video%2Fmp4&ratebypass=yes&dur=704.330&lmt=1504500896970859&mt=1565485147&fvip=2&beids=9466585&c=WEB&sparams=expire%2Cei%2Cip%2Cid%2Citag%2Csource%2Crequiressl%2Cmime%2Cratebypass%2Cdur%2Clmt&sig=ALgxI2wwRQIhAIJa8jZYZ8IlOOXu9I0zA_p97xrvDknVglPI0SmSi1y1AiAkeYNG29STkYPerBhUqpUf7YE7tZgk8k-2tzx2r_3G4w%3D%3D&lsparams=mm%2Cmn%2Cms%2Cmv%2Cmvi%2Cpl&lsig=AHylml4wRQIhAJi1xdqJEAdkSskR0gmVp_j0mxhrM87A5V7bjNGAMyr-AiBRm-zs6NdvzkpkYX0Fysyi80N2zoEe827Ckz3UL0v7_w%3D%3D", "vcodec": "avc1.64001F", "tbr": 620.007, "ext": "mp4", "player_url": "/yts/jsbin/player_ias-vfl0ft1-Z/en_US/base.js", "width": 1280, "abr": 192, "filesize": null, "fps": null, "format_id": "22", "height": 720, "quality": 2, "acodec": "mp4a.40.2"}], "playlist_uploader_id": "UC2VwgzDzUNvfRDqQ6LJxTXA", "channel_url": "http://www.youtube.com/channel/UC2VwgzDzUNvfRDqQ6LJxTXA", "resolution": null, "width": 1280, "n_entries": 483, "age_limit": 0}